{
  "songs": [
    {
      "file": "SUMMER DEEP HOUSE Musics Mix 2026 ♫ Bruno Mars, Lady Gaga,Dua Lipa, Adele,Ed Sheeran, The Weeknd #02 [gHwsEC2ducg] part1.mp3",
      "title": "SUMMER DEEP HOUSE Musics Mix 2026 part 1"
    },
    {
      "file": "SUMMER DEEP HOUSE Musics Mix 2026 ♫ Bruno Mars, Lady Gaga,Dua Lipa, Adele,Ed Sheeran, The Weeknd #02 [gHwsEC2ducg] part2.mp3",
      "title": "SUMMER DEEP HOUSE Musics Mix 2026 part 2"
    },
    {
      "file": "🎷Top 20 saxophone songs ｜ Sax House Music 2019 ｜ deep house sax ｜ saxophone🎷 [tL6oQ3pD8rI].mp3",
      "title": "Top 20 saxophone songs"
    }
  ]
}
